{
	"schemaVersion": 1,
	"id": "spiritleveling",
	"version": "${version}",
	"name": "Spirit Leveling",
	"description": "BlaBlaTODO",
	"authors": [
		"Rattenmann"
	],
	"contact": {
		"sources": "https://github.com/if24b239/spirit_leveling",
		"issues": "https://github.com/if24b239/spirit_leveling/issues"
	},
	"license": "MIT",
	"environment": "*",
	"entrypoints": {
		"main": [
			"com.rain.spiritleveling.SpiritLeveling"
		],
		"client": [
			"com.rain.spiritleveling.SpiritLevelingClient"
		],
		"fabric-datagen": [
			"com.rain.spiritleveling.SpiritLevelingDataGenerator"
		]
	},
	"mixins": [
		"spiritleveling.mixins.json"
	],
	"depends": {
		"fabricloader": ">=0.16.14",
		"minecraft": "~1.20.1",
		"java": ">=17",
		"fabric-api": "*",
		"zenith_attributes": "=0.2.10"
	},
	"suggests": {
		"modmenu-badge-lib": "*",
		"modmenu": "7.2.2"
	},
	"custom": {
		"modmenu": {
			"update_checker": true
		},
		"mcb": [
			{
				"name": "RPG",
				"labelColor": -10220268,
				"fillColor": -5429199,
				"outlineColor": -8385005
			}
		]
	}
}